pollistack/__init__.py
pollistack/client.py
pollistack-0.1.2.dist-info/METADATA
pollistack-0.1.2.dist-info/WHEEL
pollistack-0.1.2.dist-info/top_level.txt
pollistack-0.1.2.dist-info/RECORD
