Metadata-Version: 2.4
Name: pollistack
Version: 0.1.2
Summary: Python SDK for PolliStack Agent Engine
Home-page: https://github.com/pollistack/pollistack
Author: PolliStack Team
Classifier: Programming Language :: Python :: 3
Classifier: License :: OSI Approved :: MIT License
Classifier: Operating System :: OS Independent
Requires-Python: >=3.7
Requires-Dist: httpx>=0.23.0
Dynamic: author
Dynamic: classifier
Dynamic: description
Dynamic: description-content-type
Dynamic: home-page
Dynamic: requires-dist
Dynamic: requires-python
Dynamic: summary
